pattern/__init__.py
pattern/pattern.py
ranjan_pattern_printing-0.1.0.dist-info/licenses/LICENSE
ranjan_pattern_printing-0.1.0.dist-info/METADATA
ranjan_pattern_printing-0.1.0.dist-info/WHEEL
ranjan_pattern_printing-0.1.0.dist-info/top_level.txt
ranjan_pattern_printing-0.1.0.dist-info/RECORD
